UseWrapper/__init__.py
UseWrapper/core.py
usewrapper-0.1.0.dist-info/METADATA
usewrapper-0.1.0.dist-info/WHEEL
usewrapper-0.1.0.dist-info/top_level.txt
usewrapper-0.1.0.dist-info/RECORD
