Metadata-Version: 2.4
Name: usewrapper
Version: 0.1.0
Summary: A minimal utility library that showcases different prompt template styles for LLMs.
Author-email: Foresty <parthsrivastava6112004@gmail.com>
License: MIT
Project-URL: Homepage, https://github.com/Foresty/usewrapper
Project-URL: Documentation, https://github.com/Foresty/usewrapper#readme
Keywords: prompt,template,langchain,llm,ai
Classifier: Programming Language :: Python :: 3
Classifier: License :: OSI Approved :: MIT License
Classifier: Operating System :: OS Independent
Requires-Dist: rich>=13.0.0
